glcidocs/__init__.py
glcidocs/__main__.py
glcidocs/docsgen.py
glcidocs/errors.py
glcidocs/pipelineparser.py
glcidocs-0.0.1b4.dist-info/LICENSE
glcidocs-0.0.1b4.dist-info/METADATA
glcidocs-0.0.1b4.dist-info/WHEEL
glcidocs-0.0.1b4.dist-info/top_level.txt
glcidocs-0.0.1b4.dist-info/RECORD
